TpTnOsc/__init__.py
TpTnOsc/osc_exp.py
TpTnOsc/utils.py
TpTnOsc-1.2.dist-info/LICENSE.txt
TpTnOsc-1.2.dist-info/METADATA
TpTnOsc-1.2.dist-info/WHEEL
TpTnOsc-1.2.dist-info/top_level.txt
TpTnOsc-1.2.dist-info/RECORD
