Metadata-Version: 2.1
Name: TpTnOsc
Version: 1.2
Summary: Tools for analyzing TP, TN and OSC matrices
Home-page: https://github.com/yoramzarai/TpTnOsc
Author: Yoram Zarai
Author-email: yoram.zarai@gmail.com
License: MIT
Keywords: TP TN I-TN oscillatory SEB planar-network
Platform: UNKNOWN
Classifier: License :: OSI Approved :: MIT License
Classifier: Programming Language :: Python :: 3.8
Classifier: Topic :: Scientific/Engineering :: Mathematics
Requires-Python: >=3.8
Requires-Dist: numpy
Requires-Dist: scipy
Requires-Dist: networkx
Requires-Dist: matplotlib
